sqre_uservice_status-0.0.8.dist-info/DESCRIPTION.rst
sqre_uservice_status-0.0.8.dist-info/METADATA
sqre_uservice_status-0.0.8.dist-info/RECORD
sqre_uservice_status-0.0.8.dist-info/WHEEL
sqre_uservice_status-0.0.8.dist-info/entry_points.txt
sqre_uservice_status-0.0.8.dist-info/metadata.json
sqre_uservice_status-0.0.8.dist-info/top_level.txt
uservice_status/__init__.py
uservice_status/server.py
