Metadata-Version: 2.0
Name: sqre-uservice-status
Version: 0.0.8
Summary: Minimal SQuaRE API wrapper for status.lsst.codes
Home-page: https://github.com/lsst-sqre/sqre-uservice-status
Author: Adam Thornton
Author-email: athornton@lsst.org
License: MIT
Keywords: lsst
Platform: UNKNOWN
Classifier: Development Status :: 4 - Beta
Classifier: Programming Language :: Python :: 2.7
Classifier: Programming Language :: Python :: 3.5
Classifier: License :: OSI Approved :: MIT License
Requires-Dist: bitly-oauth2-proxy-session (==0.1.3)
Requires-Dist: sqre-apikit (==0.0.10)
